dialogic_dashboard/__init__.py
dialogic_dashboard/__main__.py
dialogic_dashboard/dash_app/__init__.py
dialogic_dashboard/dash_app/app_config.py
dialogic_dashboard/dash_app/auth.py
dialogic_dashboard/dash_app/views.py
dialogic_dashboard-0.0.1.dist-info/METADATA
dialogic_dashboard-0.0.1.dist-info/WHEEL
dialogic_dashboard-0.0.1.dist-info/entry_points.txt
dialogic_dashboard-0.0.1.dist-info/top_level.txt
dialogic_dashboard-0.0.1.dist-info/RECORD
