Metadata-Version: 2.1
Name: dialogic-dashboard
Version: 0.0.1
Summary: A dashboard for viewing logs of chat bots
Home-page: https://github.com/avidale/dialogic-dashboard
Author: David Dale
Author-email: dale.david@mail.ru
License: MIT
Platform: UNKNOWN
Classifier: Development Status :: 3 - Alpha
Classifier: Programming Language :: Python :: 3
Classifier: License :: OSI Approved :: MIT License
Classifier: Operating System :: OS Independent
Requires-Dist: dnspython
Requires-Dist: flask
Requires-Dist: flask-login
Requires-Dist: flask-bootstrap
Requires-Dist: pymongo
Requires-Dist: attrs
